{"alphabet": [":Int", ":Remark", ":Remark", ":Dim", ":Remark", ":Dim", ":Def", ":Remark", ":Dim", ":Def", ":Read", ":Remark", ":Dim", ":Def", ":Read", ":Goto", ":Remark", ":Dim", ":Def", ":Read", ":Goto", ":Remark", ":Dim", ":Def", ":Read", ":Goto", ":Return", ":Remark", ":Dim", ":Def", ":Read", ":Goto", ":Return", ":For", ":Remark", ":Dim", ":Def", ":Read", ":Goto", ":Return", ":For", ":Data", ":Remark", ":Dim", ":Def", ":Read", ":Goto", ":Return", ":For", ":Data", ":Gosub", ":Remark", ":Dim", ":Def", ":Read", ":Goto", ":Return", ":For", ":Data", ":Gosub", ":Print", ":Remark", ":Dim", ":Def", ":Read", ":Goto", ":Return", ":For", ":Data", ":Gosub", ":Print", ":Next", ":Remark", ":Dim", ":Def", ":Read", ":Goto", ":Return", ":For", ":Data", ":Gosub", ":Print", ":Next", ":Assign", ":Remark", ":Dim", ":Def", ":Read", ":Goto", ":Return", ":For", ":Data", ":Gosub", ":Print", ":Next", ":Assign", ":If"], "states": ["G", "K", "N", "D", "H", "J", "M", "F", "O", "I", "A", "C", "E", "B", "L"], "initial_state": "A", "accepting_states": ["C", "D", "E", "F", "G", "H", "I", "J", "K", "L", "M", "N", "O"], "transitions": [["A", ":Int", "B"], ["B", ":Remark", "K"], ["B", ":Dim", "G"], ["B", ":Def", "H"], ["B", ":Read", "L"], ["B", ":Goto", "O"], ["B", ":Return", "J"], ["B", ":For", "E"], ["B", ":Data", "M"], ["B", ":Gosub", "I"], ["B", ":Print", "N"], ["B", ":Next", "F"], ["B", ":Assign", "C"], ["B", ":If", "D"]]}